{
  "components": [
    {
      "dependencies": [
        "config-connector-darwin-arm",
        "config-connector-darwin-x86_64",
        "config-connector-linux-arm",
        "config-connector-linux-x86_64",
        "config-connector-windows-x86_64"
      ],
      "details": {
        "description": "Google Cloud Config Connector. See https://cloud.google.com/config-connector/docs/overview",
        "display_name": "config-connector"
      },
      "id": "config-connector",
      "is_configuration": false,
      "is_hidden": false,
      "is_required": false,
      "platform": {
        "architectures": [
          "arm",
          "x86_64"
        ],
        "operating_systems": [
          "LINUX",
          "MACOSX",
          "WINDOWS"
        ]
      },
      "platform_required": false,
      "version": {
        "build_number": 0,
        "version_string": "1.93.0"
      }
    }
  ],
  "revision": 20231220215703,
  "schema_version": {
    "no_update": false,
    "url": "https://dl.google.com/dl/cloudsdk/channels/rapid/google-cloud-sdk.tar.gz",
    "version": 3
  },
  "version": "458.0.1"
}